<?xml version="1.0" encoding="UTF-8" ?>
<RelativeTemporalAnnotation>
<TEXT><![CDATA[
Admission Date :
2020-05-23
Discharge Date :
2020-05-29
Service :
MEDICINE
History of Present Illness :
64 F with breast CA s/p mastectomy 17 y ago with local recurrence leading to paralysis of L arm ~ 5-6 y ago .
Now declining gradually since January ( 30 lbs weight loss , becoming more confused , decreased appetite ).
Patient declined workup / imaging for mets as outpatient .
Moving toward home hospice .
Over the last 2 weeks , husband reports patient becoming increasingly weak , unable to leave bed , confused , unable to feed herself .
Seen by VNA and noted to be tachycardic and sent to Middleborough or evaluation .
Now sent in to Amesbury by VNA because of asymptomatic sinus tachycardia .
Transferred here for workup for CNS mets and admission .
In John , VS - 99.6 , 135 , 122/65 , 20 .
Neurology evaluated pt and felt to have intact brainstem reflexes but poor prognosis .
Neurosurg evaluated pt and felt to not be surgical candidate ; recommended dilantin load and decadron .
Received lorazepam prior to CT scan .
Intubated for MS changes and lethargy and concern for airway protection .
Post intubation , hypotensive and started on dopamine and transitioned to levophed .
Received vancomycin / levafloxacin at OSH .
Received metronidazole at Ricky in Mediplex Rehab Hospital .
In CMED CCU , pt. responsive to noxious stimuli only .
History obtained from husband as above .
Brief Hospital Course :
Metastatic breast CA - Large brain mets with midline shift .
Intubated for airway protection .
Treated with IV dilantin and decadron .
Patient mental status improved slightly .
After discussion with primary oncologist goals of care where change to comfort .
Dilantin was stopped .
Will go home with prn morphine , ativan , and PR decadron .
Pnuemonia - Possible aspiration .
Completed a 7 day course of vancomycin and levofloxacin .
]]></TEXT>
<TAGS>
<RTIMEX3 id="T4" start="245" end="252" text="January" type="DATE" relative="TRUE" val="2020-01" mod="APPROX" />
<RTIMEX3 id="T6" start="628" end="631" text="Now" type="DATE" relative="TRUE" val="2020-05-23" mod="NA" />
<ATIMEX3 id="T2" start="140" end="148" text="17 y ago" type="DATE" val="2003-05-23" absolute="FALSE" mod="APPROX" />
<ATIMEX3 id="T0" start="18" end="28" text="2020-05-23" type="DATE" val="2020-05-23" absolute="TRUE" mod="NA" />
<ATIMEX3 id="T3" start="203" end="212" text="5-6 y ago" type="DATE" val="2014-11-23" absolute="FALSE" mod="APPROX" />
<ATIMEX3 id="T1" start="46" end="56" text="2020-05-29" type="DATE" val="2020-05-29" absolute="TRUE" mod="NA" />
<SECTIME id="S0" start="18" end="28" text="2020-05-23" type="ADMISSION" dvalue="2020-05-23" />
<SECTIME id="S1" start="46" end="56" text="2020-05-29" type="DISCHARGE" dvalue="2020-05-29" />
<ANCHORLINK id="AN0" fromID="T4" fromText="January" toID="S0" toText="2020-05-23" relation="BEFORE" />
<ANCHORLINK id="AN1" fromID="T2" fromText="17 y ago" toID="S0" toText="2020-05-23" relation="BEFORE" />
<ANCHORLINK id="AN2" fromID="T3" fromText="5-6 y ago" toID="S0" toText="2020-05-23" relation="BEFORE" />
<ANCHORLINK id="AN3" fromID="T6" fromText="Now" toID="S0" toText="2020-05-23" relation="EQUAL" />
</TAGS>
</RelativeTemporalAnnotation>