<ClinicalNarrativeTemporalAnnotation>
<TEXT><![CDATA[
ADMISSION DATE :
12/02/2002
DISCHARGE DATE :
12/04/2002
HISTORY OF PRESENT ILLNESS :
The patient is an 81 year old female with a history of cerebrovascular accident , atrial fibrillation , hypothyroidism and dementia who is status post laparoscopic cholecystectomy one week ago who currently presents with a 4 day history of no bowel movement .
She has complaints of abdominal distention , emesis , and constipation .
She has no chest pain , shortness of breath or fever .
She has no nausea or vomiting , chills , dysuria , hematochezia , or melena .
She was discharged from the hospital on 11/28/02 to a short term rehabilitation facility .
She was found to have normal bowel sounds .
She presented to the Ponta,itri- University Medical Center Emergency Department on 12/01/02 for evaluation of this constipation .
HOSPITAL COURSE :
The patient presented to the operating room late at night on 12/01/02 and was admitted to the floor early on the morning on 12/02/02 .
She was placed on a bowel regimen of Dulcolax , Fleet enema , and Colace .
On 12/03/02 the patient underwent a repeat KUB which was suggestive of volvulus .
She then underwent a CT scan which showed no evidence of volvulus .
Rigid sigmoidoscopy revealed no obvious mucosal abnormalities but during the time of the procedure 22cc of mucous like stool was evacuated with a large amount of gas .
Subsequent to that the patients abdomen was significantly less distended and her pain decreased as well .
On the following day , hospital day number 3 , the patient was doing well .
The abdomen was again far less distended .
She was tolerating clear liquids ad lib .
She was afebrile with stable vital signs .
A repeat KUB was performed which showed no evidence of volvulus .
She was discharged back to a rehabilitation facility in good condition .
]]></TEXT>
<TAGS>
<EVENT end="10" id="E0" modality="FACTUAL" polarity="POS" start="1" text="ADMISSION" type="OCCURRENCE"/>
<EVENT end="1015" id="E15" modality="FACTUAL" polarity="POS" start="1007" text="Dulcolax" type="TREATMENT"/>
<EVENT end="1029" id="E16" modality="FACTUAL" polarity="POS" start="1018" text="Fleet enema" type="TREATMENT"/>
<EVENT end="1042" id="E17" modality="FACTUAL" polarity="POS" start="1036" text="Colace" type="TREATMENT"/>
<EVENT end="1091" id="E18" modality="FACTUAL" polarity="POS" start="1079" text="a repeat KUB" type="TEST"/>
<EVENT end="1124" id="E19" modality="POSSIBLE" polarity="POS" start="1116" text="volvulus" type="PROBLEM"/>
<EVENT end="1155" id="E20" modality="FACTUAL" polarity="POS" start="1146" text="a CT scan" type="TEST"/>
<EVENT end="1168" id="E32" modality="FACTUAL" polarity="POS" start="1162" text="showed" type="EVIDENTIAL"/>
<EVENT end="1192" id="E50" modality="FACTUAL" polarity="NEG" start="1184" text="volvulus" type="PROBLEM"/>
<EVENT end="1214" id="E21" modality="FACTUAL" polarity="POS" start="1195" text="Rigid sigmoidoscopy" type="TEST"/>
<EVENT end="1223" id="E33" modality="FACTUAL" polarity="POS" start="1215" text="revealed" type="EVIDENTIAL"/>
<EVENT end="1256" id="E51" modality="FACTUAL" polarity="NEG" start="1227" text="obvious mucosal abnormalities" type="PROBLEM"/>
<EVENT end="1293" id="E52" modality="FACTUAL" polarity="POS" start="1280" text="the procedure" type="TEST"/>
<EVENT end="1319" id="E22" modality="FACTUAL" polarity="POS" start="1302" text="mucous like stool" type="PROBLEM"/>
<EVENT end="1333" id="E53" modality="FACTUAL" polarity="POS" start="1324" text="evacuated" type="TREATMENT"/>
<EVENT end="1360" id="E23" modality="FACTUAL" polarity="POS" start="1339" text="a large amount of gas" type="PROBLEM"/>
<EVENT end="165" id="E1" modality="FACTUAL" polarity="POS" start="141" text="cerebrovascular accident" type="PROBLEM"/>
<EVENT end="1435" id="E24" modality="FACTUAL" polarity="POS" start="1407" text="significantly less distended" type="PROBLEM"/>
<EVENT end="1448" id="E25" modality="FACTUAL" polarity="POS" start="1440" text="her pain" type="PROBLEM"/>
<EVENT end="1542" id="E57" modality="FACTUAL" polarity="POS" start="1532" text="doing well" type="EVIDENTIAL"/>
<EVENT end="1585" id="E26" modality="FACTUAL" polarity="POS" start="1567" text="far less distended" type="PROBLEM"/>
<EVENT end="1620" id="E27" modality="FACTUAL" polarity="POS" start="1607" text="clear liquids" type="TREATMENT"/>
<EVENT end="1646" id="E28" modality="FACTUAL" polarity="POS" start="1638" text="afebrile" type="PROBLEM"/>
<EVENT end="187" id="E36" modality="FACTUAL" polarity="POS" start="168" text="atrial fibrillation" type="PROBLEM"/>
<EVENT end="1685" id="E29" modality="FACTUAL" polarity="POS" start="1673" text="A repeat KUB" type="TEST"/>
<EVENT end="1712" id="E34" modality="FACTUAL" polarity="POS" start="1706" text="showed" type="EVIDENTIAL"/>
<EVENT end="1736" id="E30" modality="FACTUAL" polarity="NEG" start="1728" text="volvulus" type="PROBLEM"/>
<EVENT end="1757" id="E54" modality="FACTUAL" polarity="POS" start="1747" text="discharged" type="OCCURRENCE"/>
<EVENT end="1791" id="E55" modality="FACTUAL" polarity="POS" start="1766" text="a rehabilitation facility" type="CLINICAL_DEPT"/>
<EVENT end="1809" id="E56" modality="FACTUAL" polarity="POS" start="1795" text="good condition" type="OCCURRENCE"/>
<EVENT end="204" id="E37" modality="FACTUAL" polarity="POS" start="190" text="hypothyroidism" type="PROBLEM"/>
<EVENT end="217" id="E38" modality="FACTUAL" polarity="POS" start="209" text="dementia" type="PROBLEM"/>
<EVENT end="265" id="E2" modality="FACTUAL" polarity="POS" start="237" text="laparoscopic cholecystectomy" type="TREATMENT"/>
<EVENT end="38" id="E35" modality="FACTUAL" polarity="POS" start="29" text="DISCHARGE" type="OCCURRENCE"/>
<EVENT end="301" id="E39" modality="FACTUAL" polarity="POS" start="293" text="presents" type="OCCURRENCE"/>
<EVENT end="343" id="E40" modality="FACTUAL" polarity="NEG" start="329" text="bowel movement" type="OCCURRENCE"/>
<EVENT end="364" id="E41" modality="FACTUAL" polarity="POS" start="354" text="complaints" type="EVIDENTIAL"/>
<EVENT end="388" id="E42" modality="FACTUAL" polarity="POS" start="368" text="abdominal distention" type="PROBLEM"/>
<EVENT end="397" id="E43" modality="FACTUAL" polarity="POS" start="391" text="emesis" type="PROBLEM"/>
<EVENT end="416" id="E44" modality="FACTUAL" polarity="POS" start="404" text="constipation" type="PROBLEM"/>
<EVENT end="440" id="E3" modality="FACTUAL" polarity="NEG" start="430" text="chest pain" type="PROBLEM"/>
<EVENT end="462" id="E4" modality="FACTUAL" polarity="NEG" start="443" text="shortness of breath" type="PROBLEM"/>
<EVENT end="471" id="E5" modality="FACTUAL" polarity="NEG" start="466" text="fever" type="PROBLEM"/>
<EVENT end="491" id="E6" modality="FACTUAL" polarity="NEG" start="485" text="nausea" type="PROBLEM"/>
<EVENT end="503" id="E7" modality="FACTUAL" polarity="NEG" start="495" text="vomiting" type="PROBLEM"/>
<EVENT end="512" id="E8" modality="FACTUAL" polarity="NEG" start="506" text="chills" type="PROBLEM"/>
<EVENT end="522" id="E9" modality="FACTUAL" polarity="NEG" start="515" text="dysuria" type="PROBLEM"/>
<EVENT end="537" id="E10" modality="FACTUAL" polarity="NEG" start="525" text="hematochezia" type="PROBLEM"/>
<EVENT end="549" id="E11" modality="FACTUAL" polarity="NEG" start="543" text="melena" type="PROBLEM"/>
<EVENT end="570" id="E31" modality="FACTUAL" polarity="POS" start="560" text="discharged" type="OCCURRENCE"/>
<EVENT end="588" id="E45" modality="FACTUAL" polarity="POS" start="576" text="the hospital" type="CLINICAL_DEPT"/>
<EVENT end="640" id="E46" modality="FACTUAL" polarity="POS" start="604" text="a short term rehabilitation facility" type="CLINICAL_DEPT"/>
<EVENT end="766" id="E47" modality="FACTUAL" polarity="POS" start="704" text="the Ponta,itri- University Medical Center Emergency Department" type="CLINICAL_DEPT"/>
<EVENT end="793" id="E12" modality="FACTUAL" polarity="POS" start="783" text="evaluation" type="TEST"/>
<EVENT end="814" id="E13" modality="FACTUAL" polarity="POS" start="797" text="this constipation" type="PROBLEM"/>
<EVENT end="878" id="E48" modality="FACTUAL" polarity="POS" start="860" text="the operating room" type="CLINICAL_DEPT"/>
<EVENT end="934" id="E49" modality="FACTUAL" polarity="POS" start="925" text="the floor" type="CLINICAL_DEPT"/>
<EVENT end="1003" id="E14" modality="FACTUAL" polarity="POS" start="988" text="a bowel regimen" type="TREATMENT"/>
<ATIMEX3 end="1056" id="T3" mod="NA" start="1048" text="12/03/02" type="DATE" val="2002-12-03"/>
<RTIMEX3 end="1489" id="T9" mod="NA" start="1472" text="the following day" type="DATE" val="2002-12-04"/>
<ATIMEX3 end="28" id="T0" mod="NA" start="18" text="12/02/2002" type="DATE" val="2002-12-02"/>
<RTIMEX3 end="278" id="T5" mod="NA" start="266" text="one week ago" type="DATE" val="2002-11-25"/>

<ATIMEX3 end="56" id="T4" mod="NA" start="46" text="12/04/2002" type="DATE" val="2002-12-04"/>
<ATIMEX3 end="600" id="T1" mod="NA" start="592" text="11/28/02" type="DATE" val="2002-11-28"/>
<ATIMEX3 end="778" id="T2" mod="NA" start="770" text="12/01/02" type="DATE" val="2002-12-01"/>
<RTIMEX3 end="904" id="T7" mod="END" start="879" text="late at night on 12/01/02" type="DATE" val="2002-12-01"/>
<RTIMEX3 end="967" id="T8" mod="START" start="944" text="the morning on 12/02/02" type="DATE" val="2002-12-02"/>











































































































<SECTIME dvalue="2002-12-02" end="28" id="S0" start="18" text="12/02/2002" type="ADMISSION"/>
<SECTIME dvalue="2002-12-04" end="56" id="S1" start="46" text="12/04/2002" type="DISCHARGE"/>
</TAGS>
</ClinicalNarrativeTemporalAnnotation>